{
    "profiles": 
        [
            {   
            "id": 1,
            "nombre": "Luis Alberto Spinetta",
            "edad": 65,
            "zona": "CABA",
            "valoracion": 5,
            "email": "spinneta@gmail.com",
            "telefono": "123456789",
            "descripcion": "Lorem ipsum dolor sit amet consectetur, adipisicing elit. Excepturi reiciendis facere, velit repudiandae voluptatum est suscipit alias possimus doloribus ipsam eveniet laboriosam blanditiis. Iusto ut aperiam natus quidem quod quae?",
            "foto": "https://www.lanacion.com.ar/2150000-spinneta.jpg",
            "color": "rgb(24, 24, 44)",
            "instrumentos": [
                    "Guitarra",
                    "Bajo",
                    "Teclado",
                    "Voz"
                ],
            "generos": [
                    "Rock",
                    "Pop",
                    "Folk",
                    "Alternativo"
                ],
            "canciones": [
                            {
                            "titulo": "Barro tal vez",
                            "audio": "songs/spinetta-1.mp3"
                            },
                            {
                            "titulo": "Bajan",
                            "audio": "songs/spinetta-2.mp3"
                            },
                            {
                            "titulo": "Rezo por vos",
                            "audio": "songs/spinetta-3.mp3"
                            },
                            {
                            "titulo": "Muchacha ojos de papel",
                            "audio": "songs/spinetta-4.mp3"
                            }
                ]
            },
            {   
            "id": 2,
            "nombre": "Wos",
            "edad": 24,
            "zona": "CABA",
            "valoracion": 5,
            "email": "wosito@gmail.com",
            "telefono": "123456789",
            "descripcion": "Lorem ipsum dolor sit amet consectetur, adipisicing elit. Excepturi reiciendis facere, velit repudiandae voluptatum est suscipit alias possimus doloribus ipsam eveniet laboriosam blanditiis. Iusto ut aperiam natus quidem quod quae?",
            "foto": "https://www.lanacion.com.ar/2150000-charly.jpg",
            "color": "rgb(61, 129, 61)",
            "instrumentos": [
                    "Voz",
                    "Caja de ritmo",
                    "Batería"
                ],
            "generos": [
                    "Rap",
                    "Hip-Hop",
                    "Pop urbano"
                ],
            "canciones": [
                    {
                    "titulo": "Arrancarmelo",
                    "audio": "songs/wos-1.mp3"
                    },
                    {
                    "titulo": "Alma dinamita",
                    "audio": "songs/wos-2.mp3"
                    },
                    {
                    "titulo": "Canguro",
                    "audio": "songs/wos-3.mp3"
                    },
                    {
                    "titulo": "Quereme",
                    "audio": "songs/wos-4.mp3"
                    }
            ]
            },
            {   
            "id": 3,
            "nombre": "María Becerra",
            "edad": 23,
            "zona": "CABA",
            "valoracion": 5,
            "email": "becerra@gmail.com",
            "telefono": "123456789",
            "descripcion": "Lorem ipsum dolor sit amet consectetur, adipisicing elit. Excepturi reiciendis facere, velit repudiandae voluptatum est suscipit alias possimus doloribus ipsam eveniet laboriosam blanditiis. Iusto ut aperiam natus quidem quod quae?",
            "foto": "https://www.lanacion.com.ar/2150000-charly.jpg",
            "color": "rgb(151, 39, 151)",
            "instrumentos": [
                    "Voz",
                    "Piano"
                ],
            "generos": [
                    "Reggaeton",
                    "Pop urbano"
                ],
            "canciones": [
                    {
                    "titulo": "Acaramelao",
                    "audio": "songs/becerra-1.mp3"
                    },
                    {
                    "titulo": "Automático",
                    "audio": "songs/becerra-2.mp3"
                    },
                    {
                    "titulo": "Ojalá",
                    "audio": "songs/becerra-3.mp3"
                    },
                    {
                    "titulo": "High",
                    "audio": "songs/becerra-4.mp3"
                    }
            ]
            },
            {   
            "id": 4,
            "nombre": "La Rosalía",
            "edad": 28,
            "zona": "Barcelona",
            "valoracion": 5,
            "email": "conaltura@gmail.com",
            "telefono": "123456789",
            "descripcion": "Lorem ipsum dolor sit amet consectetur, adipisicing elit. Excepturi reiciendis facere, velit repudiandae voluptatum est suscipit alias possimus doloribus ipsam eveniet laboriosam blanditiis. Iusto ut aperiam natus quidem quod quae?",
            "foto": "https://www.lanacion.com.ar/2150000-charly.jpg",
            "color": "rgb(190, 19, 19)",
            "instrumentos": [
                    "Voz",
                    "Castañuelas",
                    "Guitarra"
                ],
            "generos": [
                    "Flamenco",
                    "Pop urbano",
                    "Reggaeton"
                ],
            "canciones": [
                    {
                    "titulo": "Con altura",
                    "audio": "songs/rosalia-1.mp3"
                    },
                    {
                    "titulo": "Millonaria",
                    "audio": "songs/rosalia-2.mp3"
                    },
                    {
                    "titulo": "Hentai",
                    "audio": "songs/rosalia-3.mp3"
                    },
                    {
                    "titulo": "Despechá",
                    "audio": "songs/rosalia-4.mp3"
                    }
            ]
            }
        ]
    
}